Metadata-Version: 2.4
Name: getstream-plugins-fal
Version: 0.1.1
Summary: Fal.ai plugin for GetStream
License-Expression: MIT
Requires-Python: >=3.10
Requires-Dist: fal-client>=0.7.0
Requires-Dist: getstream-plugins-common>=0.1.0
Requires-Dist: getstream[webrtc]>=2.3.0a4
